truelayer/__init__.py
truelayer/api_client.py
truelayer/configuration.py
truelayer/exceptions.py
truelayer/fields.py
truelayer/rest.py
truelayer/api/__init__.py
truelayer/api/data_api.py
truelayer/auth/__init__.py
truelayer/auth/api_client.py
truelayer/auth/configuration.py
truelayer/auth/exceptions.py
truelayer/auth/fields.py
truelayer/auth/rest.py
truelayer/auth/api/__init__.py
truelayer/auth/api/auth_api.py
truelayer/auth/api/data_api.py
truelayer/auth/models/__init__.py
truelayer/auth/models/provider.py
truelayer/auth/models/token_response.py
truelayer/auth/test/__init__.py
truelayer/auth/test/test_auth_api.py
truelayer/auth/test/test_data_api.py
truelayer/auth/test/test_provider.py
truelayer/auth/test/test_token_response.py
truelayer/models/__init__.py
truelayer/models/account.py
truelayer/models/account_number.py
truelayer/models/address_info.py
truelayer/models/api_response_account.py
truelayer/models/api_response_balance.py
truelayer/models/api_response_card.py
truelayer/models/api_response_card_balance.py
truelayer/models/api_response_card_transaction.py
truelayer/models/api_response_info.py
truelayer/models/api_response_me.py
truelayer/models/api_response_transaction.py
truelayer/models/balance.py
truelayer/models/cached_api_response_object.py
truelayer/models/card.py
truelayer/models/card_balance.py
truelayer/models/card_transaction.py
truelayer/models/info.py
truelayer/models/me.py
truelayer/models/provider_info.py
truelayer/models/transaction.py
pytruelayer-0.3.0.dist-info/METADATA
pytruelayer-0.3.0.dist-info/WHEEL
pytruelayer-0.3.0.dist-info/top_level.txt
pytruelayer-0.3.0.dist-info/RECORD
