Metadata-Version: 2.1
Name: pytruelayer
Version: 0.3.0
Summary: TrueLayer Resource API
Home-page: UNKNOWN
Author: TrueLayer.com
Author-email: rienafairefr@gmail.com
License: UNKNOWN
Keywords: OpenAPI,OpenAPI-Generator,TrueLayer Resource API
Platform: UNKNOWN
Requires-Dist: urllib3 (>=1.15)
Requires-Dist: six (>=1.10)
Requires-Dist: certifi
Requires-Dist: python-dateutil
Requires-Dist: marshmallow
